bp_libc_got/__init__.py
bp_libc_got/main.py
bp_libc_got/util.py
bp_libc_got-0.0.1.dist-info/LICENSE
bp_libc_got-0.0.1.dist-info/METADATA
bp_libc_got-0.0.1.dist-info/WHEEL
bp_libc_got-0.0.1.dist-info/top_level.txt
bp_libc_got-0.0.1.dist-info/RECORD
