Metadata-Version: 2.1
Name: bp_libc_got
Version: 0.0.1
Summary: Breakpoint at the address in the .got.plt section of the libraries loaded in the target process
Home-page: https://github.com/h1ghl1kh7/bp-libc-got
Classifier: Programming Language :: Python :: 3
Classifier: Programming Language :: Python :: 3.8
Requires-Python: >=3.8
License-File: LICENSE
